pr22/__init__.py
pr22/__main__.py
pr22/control.py
pr22/core.py
pr22/ecardhandling.py
pr22/exceptions.py
pr22/fieldid.py
pr22/imaging.py
pr22/prins.py
pr22/processing.py
pr22/task.py
pr22/types.py
pr22/util.py
pr22-2.2.0.22.dist-info/METADATA
pr22-2.2.0.22.dist-info/WHEEL
pr22-2.2.0.22.dist-info/licenses/LICENSE
pr22-2.2.0.22.dist-info/RECORD
