Metadata-Version: 2.4
Name: pr22
Version: 2.2.0.22
Summary: Passport Reader Interface
Project-URL: Homepage, https://adaptiverecognition.com/personal-document-reading-and-verification/
Project-URL: Technical Support, https://adaptiverecognition.com/support/
License-Expression: MIT
License-File: LICENSE
Requires-Python: >=3.6
